Decoder.v


module Decoder #(
    parameter POLY_SIZE = 16,       // Number of coefficients
    parameter OUTPUT_WIDTH = 16,   // Bit width of the output binary data
    parameter SCALE_FACTOR = 2    // Scaling factor used during encoding
)(
    input [(OUTPUT_WIDTH+SCALE_FACTOR)*POLY_SIZE-1:0] poly_coeff, // Flattened array
    output reg [OUTPUT_WIDTH-1:0] binary_data // Decoded binary data
);

reg [OUTPUT_WIDTH+SCALE_FACTOR-1:0] selected_coeff; // To hold the selected coefficient

always @(*) begin
    // Extract the selected coefficient from the flattened array
    selected_coeff = poly_coeff[(OUTPUT_WIDTH+SCALE_FACTOR)-1 -: (OUTPUT_WIDTH+SCALE_FACTOR)];
    // Perform reverse scaling
    binary_data <= selected_coeff >> SCALE_FACTOR;
end

endmodule

Encoder.v

module Encoder #(
    parameter POLY_SIZE = 16,
    parameter INPUT_WIDTH = 16,
    parameter SCALE_FACTOR = 2
    )(
        input clk,
        input reset,
        input [INPUT_WIDTH-1:0] binary_data,
        output reg [(INPUT_WIDTH+SCALE_FACTOR)*POLY_SIZE-1:0] poly_coeff
        );  

integer i;
reg [INPUT_WIDTH + SCALE_FACTOR-1:0] poly_internal[0:POLY_SIZE-1]; // Internal unpacked array

//1st always block
always@(posedge clk or posedge reset)
begin
  if(reset)
    begin
    for(i=0;i<POLY_SIZE;i++)
        begin
            poly_internal[i] <= 0; //reset the polynomial coeffiecients
        end
    end

  else 
    begin
    for(i=0;i<POLY_SIZE;i++)
        begin
            poly_internal[i] <= binary_data << SCALE_FACTOR; //scale the input data by the scaling factor ie(i/p*2^10)
        end 
    end
end

//2nd always block
always @(*) begin
    for (i = 0; i < POLY_SIZE; i = i + 1) begin
        poly_coeff[(i+1)*(INPUT_WIDTH+SCALE_FACTOR)-1 -: (INPUT_WIDTH+SCALE_FACTOR)] = poly_internal[i];
    end
end

 endmodule

En_De_Top.v
`include "Encoder.v"
`include "Decoder.v"


module En_De_Top #( 
    parameter DATA_SIZE = 16,
    parameter POLY_SIZE = 16,
    parameter SCALE_FACTOR = 2

)(   
    input clk,
    input reset,
    input [DATA_SIZE-1:0] data_in,
    output[(DATA_SIZE+SCALE_FACTOR)*POLY_SIZE-1:0] encoded_data,
    output [DATA_SIZE-1:0] data_out
);


wire [(DATA_SIZE+SCALE_FACTOR)*POLY_SIZE-1:0] w_encoded_data;

//module instantiation 

Encoder E1 (.clk(clk),.reset(reset),.binary_data(data_in),.poly_coeff(w_encoded_data));
Decoder D1 (.poly_coeff(w_encoded_data),.binary_data(data_out));

assign encoded_data = w_encoded_data;

endmodule

En_De_Top_tb.v

`include "En_De_Top.v"

module En_De_Top_tb;

    // Parameters
    parameter DATA_SIZE = 16;
    parameter POLY_SIZE = 16;
    parameter SCALE_FACTOR = 2;

    // Testbench Signals
    reg clk;
    reg reset;
    reg [DATA_SIZE-1:0] data_in;
    wire [(DATA_SIZE+SCALE_FACTOR)*POLY_SIZE-1:0] encoded_data;
    wire [DATA_SIZE-1:0] data_out;

    // Instantiate the DUT (Device Under Test)
    En_De_Top #(
        .DATA_SIZE(DATA_SIZE),
        .POLY_SIZE(POLY_SIZE),
        .SCALE_FACTOR(SCALE_FACTOR)
    ) DUT (
        .clk(clk),
        .reset(reset),
        .data_in(data_in),
        .encoded_data(encoded_data),
        .data_out(data_out)
    );

    // Clock Generation
    initial begin
        clk = 0;
        forever #5 clk = ~clk; // 100 MHz clock (10 ns period)
    end

    // Test Procedure
    initial begin
        // Initialize Inputs
        reset = 1;
        data_in = 0;

        // Apply Reset
        #20 reset = 0; // Deassert reset after 20 ns

        // Test Case 1: Input data = 5
        #10 data_in = 5;
        #20; // Wait for processing

        // Check outputs
        $display("Input: %d, Encoded: %d, Decoded: %d", data_in, encoded_data, data_out);

        // Test Case 2: Input data = 25
        #10 data_in = 25;
        #20; // Wait for processing

        // Check outputs
        $display("Input: %d, Encoded: %d, Decoded: %d", data_in, encoded_data, data_out);

        // Test Case 3: Input data = 123
        #10 data_in = 123;
        #20; // Wait for processing

        // Check outputs
        $display("Input: %d, Encoded: %d, Decoded: %d", data_in, encoded_data, data_out);

        // Test Case 4: Edge case: Input data = 0
        #10 data_in = 0;
        #20; // Wait for processing

        // Check outputs
        $display("Input: %d, Encoded: %d, Decoded: %d", data_in, encoded_data, data_out);

        // Test Case 5: Edge case: Maximum Input
        #10 data_in = (2**DATA_SIZE)-1; // Max input for 16-bit data
        #20; // Wait for processing

        // Check outputs
        $display("Input: %d, Encoded: %d, Decoded: %d", data_in, encoded_data, data_out);

        // End simulation
        #50 $finish;
    end

    initial
begin
  $dumpfile("output.vcd");
  $dumpvars(1);
  
end

endmodule

output.vcd
$date
	Wed Dec 18 14:01:41 2024
$end
$version
	Icarus Verilog
$end
$timescale
	1s
$end
$scope module En_De_Top_tb $end
$var wire 288 ! encoded_data [287:0] $end
$var wire 16 " data_out [15:0] $end
$var reg 1 # clk $end
$var reg 16 $ data_in [15:0] $end
$var reg 1 % reset $end
$upscope $end
$enddefinitions $end
#0
$dumpvars
1%
b0 $
0#
b0 "
b0 !
$end
#5
1#
#10
0#
#15
1#
#20
0#
0%
#25
1#
#30
0#
b101 $
#35
b101 "
b10100000000000000010100000000000000010100000000000000010100000000000000010100000000000000010100000000000000010100000000000000010100000000000000010100000000000000010100000000000000010100000000000000010100000000000000010100000000000000010100000000000000010100000000000000010100 !
1#
#40
0#
#45
1#
#50
0#
#55
1#
#60
0#
b11001 $
#65
b11001 "
b1100100000000000001100100000000000001100100000000000001100100000000000001100100000000000001100100000000000001100100000000000001100100000000000001100100000000000001100100000000000001100100000000000001100100000000000001100100000000000001100100000000000001100100000000000001100100 !
1#
#70
0#
#75
1#
#80
0#
#85
1#
#90
0#
b1111011 $
#95
b1111011 "
b111101100000000000111101100000000000111101100000000000111101100000000000111101100000000000111101100000000000111101100000000000111101100000000000111101100000000000111101100000000000111101100000000000111101100000000000111101100000000000111101100000000000111101100000000000111101100 !
1#
#100
0#
#105
1#
#110
0#
#115
1#
#120
0#
b0 $
#125
b0 "
b0 !
1#
#130
0#
#135
1#
#140
0#
#145
1#
#150
0#
b1111111111111111 $
#155
b1111111111111111 "
b111111111111111100111111111111111100111111111111111100111111111111111100111111111111111100111111111111111100111111111111111100111111111111111100111111111111111100111111111111111100111111111111111100111111111111111100111111111111111100111111111111111100111111111111111100111111111111111100 !
1#
